subweb/__init__.py
subweb/subdomain.py
subweb-2.0.1.dist-info/METADATA
subweb-2.0.1.dist-info/WHEEL
subweb-2.0.1.dist-info/top_level.txt
subweb-2.0.1.dist-info/RECORD
