Metadata-Version: 2.1
Name: subweb
Version: 2.0.1
Summary: A package for scanning subdomains and collecting website information.
Home-page: https://github.com/ByteBreach/subweb
Author: MrFidal
Author-email: mrfidal@proton.me
Keywords: subdomain scanning web scraping information
Classifier: Programming Language :: Python :: 3
Classifier: License :: OSI Approved :: MIT License
Classifier: Operating System :: OS Independent
Classifier: Topic :: Internet :: WWW/HTTP
Classifier: Topic :: Security
Requires-Dist: requests
